setup.py
notification_schedule_library/__init__.py
notification_schedule_library.egg-info/PKG-INFO
notification_schedule_library.egg-info/SOURCES.txt
notification_schedule_library.egg-info/dependency_links.txt
notification_schedule_library.egg-info/requires.txt
notification_schedule_library.egg-info/top_level.txt