Metadata-Version: 2.1
Name: notification_schedule_library
Version: 0.5
Summary: A library for handling notifications.
Home-page: https://github.com/gabrfern99/notification_library
Author: Gabriel
Author-email: gabr.fern99@gmail.com
Classifier: Programming Language :: Python :: 3
Classifier: License :: OSI Approved :: MIT License
Classifier: Operating System :: OS Independent
Requires-Python: >=3.6
Requires-Dist: requests
